synthfuse/__init__.py
synthfuse/__main__.py
synthfuse/agents/base.py
synthfuse/agents/hub.py
synthfuse/alchemj/__init__.py
synthfuse/alchemj/ast.py
synthfuse/alchemj/compiler.py
synthfuse/alchemj/registry.py
synthfuse/alchemj/plugins/__init__.py
synthfuse/alchemj/plugins/numeric.py
synthfuse/alchemj/plugins/orion.py
synthfuse/alchemj/plugins/rl.py
synthfuse/alchemj/plugins/sat.py
synthfuse/alchemj/plugins/sql.py
synthfuse/alchemj/plugins/swarm.py
synthfuse/alchemj/plugins/util.py
synthfuse/cabinet/cabinet_orchestrator.py
synthfuse/meta/__init__.py
synthfuse/meta/constitution.py
synthfuse/meta/diagnostic.py
synthfuse/meta/diagnostics.py
synthfuse/meta/engineer_alchemist.py
synthfuse/meta/gradient_clip.py
synthfuse/meta/meta_alchemist.py
synthfuse/meta/regulator.py
synthfuse/meta/rollback.py
synthfuse/meta/safe_macro.py
synthfuse/meta/sql_constitution.py
synthfuse/meta/sql_diagnostics.py
synthfuse/meta/zeta_alchemist.py
synthfuse/notebook/__init__.py
synthfuse/notebook/cell.py
synthfuse/notebook/checkpoint.py
synthfuse/notebook/kernel.py
synthfuse/notebook/sql_widgets.py
synthfuse/notebook/viz.py
synthfuse/notebook/widgets.py
synthfuse/pipeline/fluid_ingestion.py
synthfuse/pipeline/unified_vector_pipeline.py
synthfuse/recipes/__init__.py
synthfuse/recipes/aquaorion_llm.py
synthfuse/recipes/auto_fusion.py
synthfuse/recipes/bio_fusion.py
synthfuse/recipes/canch.py
synthfuse/recipes/conv_lstm_ae.py
synthfuse/recipes/crypto_fusion.py
synthfuse/recipes/dl4sci_fusion.py
synthfuse/recipes/edge_fusion.py
synthfuse/recipes/fql_rime.py
synthfuse/recipes/gmm_poly_reg.py
synthfuse/recipes/graph_fusion.py
synthfuse/recipes/knn_boost_rf.py
synthfuse/recipes/meta_fusion.py
synthfuse/recipes/mrbmo_ppo.py
synthfuse/recipes/poly_svr_tree.py
synthfuse/recipes/rflf.py
synthfuse/recipes/robo_fusion.py
synthfuse/recipes/shimmy_fusion.py
synthfuse/recipes/syn_fusion.py
synthfuse/recipes/time_fusion.py
synthfuse/recipes/3rd-party/brpc_fusion.py
synthfuse/recipes/3rd-party/fate_fusion.py
synthfuse-0.2.0.dist-info/METADATA
synthfuse-0.2.0.dist-info/WHEEL
synthfuse-0.2.0.dist-info/entry_points.txt
synthfuse-0.2.0.dist-info/top_level.txt
synthfuse-0.2.0.dist-info/RECORD
